jupyter_suggestions/__init__.py
jupyter_suggestions-0.1.1.dist-info/METADATA
jupyter_suggestions-0.1.1.dist-info/WHEEL
jupyter_suggestions-0.1.1.dist-info/licenses/LICENSE
jupyter_suggestions-0.1.1.dist-info/RECORD
